DSD/Lab3/Q4/GtoB.v
module GtoB(g,b);
parameter n=4;
input [n-1:0]g;
output reg [n-1:0]b;
integer i;
always @*
begin
	b[n-1]=g[n-1];
	for(i=n-2;i>=0;i=i-1)
		b[i]=b[i+1]^g[i];
end
endmodule

DSD/Lab3/Q4/GtoB_tb.v
`timescale 1ns/1ns
`include "GtoB.v"
module GtoB_tb;
reg [3:0]g;
wire [3:0]b;
GtoB g1(g,b);
initial begin
	$dumpfile("GtoB_tb.vcd");
	$dumpvars(0,GtoB_tb);
	g=4'b0000;
	#20;
	g=4'b0001;
	#20;
	g=4'b0010;
	#20;
	g=4'b0011;
	#20;
	g=4'b0100;
	#20;
	g=4'b0101;
	#20;
	g=4'b0110;
	#20;
	g=4'b0111;
	#20;
	g=4'b1000;
	#20;
	g=4'b1001;
	#20;
	g=4'b1010;
	#20;
	g=4'b1011;
	#20;
	g=4'b1100;
	#20;
	g=4'b1101;
	#20;
	g=4'b1110;
	#20;
	g=4'b1111;
	#20;
end
endmodule

DSD/Lab3/Q4/GtoB_tb.vcd
$date
	Thu Aug 24 11:03:54 2023
$end
$version
	Icarus Verilog
$end
$timescale
	1ns
$end
$scope module GtoB_tb $end
$var wire 4 ! b [3:0] $end
$var reg 4 " g [3:0] $end
$scope module g1 $end
$var wire 4 # g [3:0] $end
$var reg 4 $ b [3:0] $end
$var integer 32 % i [31:0] $end
$upscope $end
$upscope $end
$enddefinitions $end
#0
$dumpvars
b11111111111111111111111111111111 %
b0 $
b0 #
b0 "
b0 !
$end
#20
b1 !
b1 $
b11111111111111111111111111111111 %
b1 "
b1 #
#40
b11 !
b11 $
b11111111111111111111111111111111 %
b10 "
b10 #
#60
b10 !
b10 $
b11111111111111111111111111111111 %
b11 "
b11 #
#80
b111 !
b111 $
b11111111111111111111111111111111 %
b100 "
b100 #
#100
b110 !
b110 $
b11111111111111111111111111111111 %
b101 "
b101 #
#120
b100 !
b100 $
b11111111111111111111111111111111 %
b110 "
b110 #
#140
b101 !
b101 $
b11111111111111111111111111111111 %
b111 "
b111 #
#160
b11111111111111111111111111111111 %
b1111 !
b1111 $
b1000 "
b1000 #
#180
b1110 !
b1110 $
b11111111111111111111111111111111 %
b1001 "
b1001 #
#200
b1100 !
b1100 $
b11111111111111111111111111111111 %
b1010 "
b1010 #
#220
b1101 !
b1101 $
b11111111111111111111111111111111 %
b1011 "
b1011 #
#240
b1000 !
b1000 $
b11111111111111111111111111111111 %
b1100 "
b1100 #
#260
b1001 !
b1001 $
b11111111111111111111111111111111 %
b1101 "
b1101 #
#280
b1011 !
b1011 $
b11111111111111111111111111111111 %
b1110 "
b1110 #
#300
b1010 !
b1010 $
b11111111111111111111111111111111 %
b1111 "
b1111 #
