DSD/Lab2/FullAdder/FAdder.v
module FAdder(a,b,cin,s,cout);
input a,b,cin;
output s,cout;
assign s=a^b^cin;
assign cout=(a&b)|(b&cin)|(cin&a);
endmodule

DSD/Lab2/FullAdder/FAdder_tb.v
`timescale 1ns/1ns
`include "FAdder.v"
module FAdder_tb;
reg x1,x2,x3;
wire s,cout;
FAdder F1(x1,x2,x3,s,cout);
initial begin
	$dumpfile("FAdder_tb.vcd");
	$dumpvars(0,FAdder_tb);
	x1=0;
	x2=0;
	x3=0;
	#10;
	x1=0;
	x2=0;
	x3=1;
	#10;
	x1=0;
	x2=1;
	x3=0;
	#10;
	x1=0;
	x2=1;
	x3=1;
	#10;
	x1=1;
	x2=0;
	x3=0;
	#10;
	x1=1;
	x2=0;
	x3=1;
	#10;
	x1=1;
	x2=1;
	x3=0;
	#10;
	x1=1;
	x2=1;
	x3=1;
	#10;
	$display("Test_completed");
end
endmodule

DSD/Lab2/FullAdder/FAdder_tb.vcd
$date
	Thu Aug 17 09:41:43 2023
$end
$version
	Icarus Verilog
$end
$timescale
	1ns
$end
$scope module FAdder_tb $end
$var wire 1 ! s $end
$var wire 1 " cout $end
$var reg 1 # x1 $end
$var reg 1 $ x2 $end
$var reg 1 % x3 $end
$scope module F1 $end
$var wire 1 # a $end
$var wire 1 $ b $end
$var wire 1 % cin $end
$var wire 1 " cout $end
$var wire 1 ! s $end
$upscope $end
$upscope $end
$enddefinitions $end
#0
$dumpvars
0%
0$
0#
0"
0!
$end
#10
1!
1%
#20
0%
1$
#30
1"
0!
1%
#40
0"
1!
0%
0$
1#
#50
1"
0!
1%
#60
0%
1$
#70
1!
1%
