DSD/Lab4/dec2to4/dec2to4.v
module dec2to4(W,Y,En);
input [1:0]W;
input En;
output reg [0:3]Y;
always@*
begin
if(En==1)
begin
if(W==0)
Y=4'b1000;
else if(W==1)
Y=4'b0100;
else if(W==2)
Y=4'b0010;
else
Y=4'b0001;
end
else
Y=4'b0000;
end
endmodule

DSD/Lab5/Q3/dec4to16.v
`include "dec2to4.v"
module dec4to16(W,Y,En);
input [3:0]W;
input En;
output [0:15]Y;
wire [0:3]M;
dec2to4 d1(W[3:2],M,En);
dec2to4 d2(W[1:0],Y[0:3],M[0]);
dec2to4 d3(W[1:0],Y[4:7],M[1]);
dec2to4 d4(W[1:0],Y[8:11],M[2]);
dec2to4 d5(W[1:0],Y[12:15],M[3]);
endmodule

DSD/Lab4/dec4to16/dec4to16_tb.v
`timescale 1ns/1ns
`include "dec4to16.v"
module dec4to16_tb;
reg [3:0]W;
wire [0:15]Y;
reg En;
dec4to16 d(W,Y,En);
initial begin
$dumpfile("dec4to16_tb.vcd");
$dumpvars(0,dec4to16_tb);
W=0;En=1;
#10;
W=1;En=1;
#10;
W=2;En=1;
#10;
W=3;En=1;
#10;
W=4;En=1;
#10;
W=5;En=1;
#10;
W=6;En=1;
#10;
W=7;En=1;
#10;
W=8;En=1;
#10;
W=9;En=1;
#10;
W=10;En=1;
#10;
W=11;En=1;
#10;
W=12;En=1;
#10;
W=13;En=1;
#10;
W=14;En=1;
#10;
W=15;En=1;
#10;
end
endmodule

DSD/Lab4/dec4to16/dec4to16_tb.vcd
$date
	Thu Aug 31 09:30:57 2023
$end
$version
	Icarus Verilog
$end
$timescale
	1ns
$end
$scope module dec4to16_tb $end
$var wire 16 ! Y [0:15] $end
$var reg 1 " En $end
$var reg 4 # W [3:0] $end
$scope module d $end
$var wire 1 " En $end
$var wire 4 $ W [3:0] $end
$var wire 16 % Y [0:15] $end
$var wire 4 & M [0:3] $end
$scope module d1 $end
$var wire 1 " En $end
$var wire 2 ' W [1:0] $end
$var reg 4 ( Y [0:3] $end
$upscope $end
$scope module d2 $end
$var wire 1 ) En $end
$var wire 2 * W [1:0] $end
$var reg 4 + Y [0:3] $end
$upscope $end
$scope module d3 $end
$var wire 1 , En $end
$var wire 2 - W [1:0] $end
$var reg 4 . Y [0:3] $end
$upscope $end
$scope module d4 $end
$var wire 1 / En $end
$var wire 2 0 W [1:0] $end
$var reg 4 1 Y [0:3] $end
$upscope $end
$scope module d5 $end
$var wire 1 2 En $end
$var wire 2 3 W [1:0] $end
$var reg 4 4 Y [0:3] $end
$upscope $end
$upscope $end
$upscope $end
$enddefinitions $end
#0
$dumpvars
b0 4
b0 3
02
b0 1
b0 0
0/
b0 .
b0 -
0,
b1000 +
b0 *
1)
b1000 (
b0 '
b1000 &
b1000000000000000 %
b0 $
b0 #
1"
b1000000000000000 !
$end
#10
b100000000000000 !
b100000000000000 %
b100 +
b1 *
b1 -
b1 0
b1 3
b1 #
b1 $
#20
b10000000000000 !
b10000000000000 %
b10 +
b10 *
b10 -
b10 0
b10 3
b10 #
b10 $
#30
b1000000000000 !
b1000000000000 %
b1 +
b11 *
b11 -
b11 0
b11 3
b11 #
b11 $
#40
b1000 .
1,
0)
b100 &
b100 (
b100000000000 !
b100000000000 %
b0 +
b1 '
b0 *
b0 -
b0 0
b0 3
b100 #
b100 $
#50
b10000000000 !
b10000000000 %
b100 .
b1 *
b1 -
b1 0
b1 3
b101 #
b101 $
#60
b1000000000 !
b1000000000 %
b10 .
b10 *
b10 -
b10 0
b10 3
b110 #
b110 $
#70
b100000000 !
b100000000 %
b1 .
b11 *
b11 -
b11 0
b11 3
b111 #
b111 $
#80
b1000 1
1/
0,
b10 &
b10 (
b10000000 !
b10000000 %
b0 .
b10 '
b0 *
b0 -
b0 0
b0 3
b1000 #
b1000 $
#90
b1000000 !
b1000000 %
b100 1
b1 *
b1 -
b1 0
b1 3
b1001 #
b1001 $
#100
b100000 !
b100000 %
b10 1
b10 *
b10 -
b10 0
b10 3
b1010 #
b1010 $
#110
b10000 !
b10000 %
b1 1
b11 *
b11 -
b11 0
b11 3
b1011 #
b1011 $
#120
b1000 4
12
0/
b1 &
b1 (
b1000 !
b1000 %
b0 1
b11 '
b0 *
b0 -
b0 0
b0 3
b1100 #
b1100 $
#130
b100 !
b100 %
b100 4
b1 *
b1 -
b1 0
b1 3
b1101 #
b1101 $
#140
b10 !
b10 %
b10 4
b10 *
b10 -
b10 0
b10 3
b1110 #
b1110 $
#150
b1 !
b1 %
b1 4
b11 *
b11 -
b11 0
b11 3
b1111 #
b1111 $
