DSD/Lab9/Q1/R_4.v
module R_4(reset,clk,c);
input reset,clk;
output [3:0]c;
reg [3:0]t;
always@(posedge(clk) or reset)
begin
if(reset)
	t=4'b1000;
else
begin
	t={t[0],t[3:1]};
end
end
assign c=t;
endmodule

DSD/Lab9/Q1/R_4_tb.v
`timescale 1ns/1ns
`include "R_4.v"
module R_4_tb;
reg reset,clk;
wire [3:0]c;
R_4 R(reset,clk,c);
always #10 clk=~clk;
initial begin
$dumpfile("R_4_tb.vcd");
$dumpvars(0,R_4_tb);
clk=0;
end
initial begin
	reset=1'b1;#20;
	reset=1'b0;#20;
	reset=1'b0;#20;
	reset=1'b0;#20;
	reset=1'b0;#20;
	reset=1'b0;#20;
	reset=1'b0;#20;
$finish;
end
endmodule

DSD/Lab9/Q1/R_4_tb.vcd
$date
	Thu Oct 26 09:38:17 2023
$end
$version
	Icarus Verilog
$end
$timescale
	1ns
$end
$scope module R_4_tb $end
$var wire 4 ! c [3:0] $end
$var reg 1 " clk $end
$var reg 1 # reset $end
$scope module R $end
$var wire 4 $ c [3:0] $end
$var wire 1 " clk $end
$var wire 1 # reset $end
$var reg 4 % t [3:0] $end
$upscope $end
$upscope $end
$enddefinitions $end
#0
$dumpvars
b1000 %
b1000 $
1#
0"
b1000 !
$end
#10
1"
#20
b100 !
b100 $
b100 %
0"
0#
#30
b10 !
b10 $
b10 %
1"
#40
0"
#50
b1 !
b1 $
b1 %
1"
#60
0"
#70
b1000 !
b1000 $
b1000 %
1"
#80
0"
#90
b100 !
b100 $
b100 %
1"
#100
0"
#110
b10 !
b10 $
b10 %
1"
#120
0"
#130
b1 !
b1 $
b1 %
1"
