DSD/Lab5/Q1/q1.v
module FourtoOne(W,S,f);
input [0:3]W;
input [1:0]S;
output reg f;
always @*
begin
if(S==0)
	f=W[0];
else if (S==1)
	f=W[1];
else if (S==2)
	f=W[2];
else
	f=W[3];
end
endmodule

module q1(W,f);
input [0:3]W;
output f;
wire [0:3]M;
assign M[0]=~(W[2]&W[3]);
assign M[2]=((~(W[2]))&(W[3]));
assign M[1]=~(W[3]);
assign M[3]=~(W[3]);
FourtoOne w1 (M,W[0:1],f);
endmodule

DSD/Lab5/Q1/q1_tb.v
`timescale 1ns/1ns
`include "q1.v"
module q1_tb;
reg [0:3]W;
wire f;
integer i;
q1 q(W,f);
initial begin
$dumpfile("q1_tb.vcd");
$dumpvars(0,q1_tb);
for(i=0;i<16;i=i+1)
begin
W=i;
#10;
end
end
endmodule

DSD/Lab5/Q1/q1_tb.vcd
$date
	Thu Sep 14 09:30:21 2023
$end
$version
	Icarus Verilog
$end
$timescale
	1ns
$end
$scope module q1_tb $end
$var wire 1 ! f $end
$var reg 4 " W [0:3] $end
$var integer 32 # i [31:0] $end
$scope module q $end
$var wire 4 $ W [0:3] $end
$var wire 1 ! f $end
$var wire 4 % M [0:3] $end
$scope module w1 $end
$var wire 2 & S [1:0] $end
$var wire 4 ' W [0:3] $end
$var reg 1 ! f $end
$upscope $end
$upscope $end
$upscope $end
$enddefinitions $end
#0
$dumpvars
b1101 '
b0 &
b1101 %
b0 $
b0 #
b0 "
1!
$end
#10
b1010 %
b1010 '
b1 "
b1 $
b1 #
#20
b1101 %
b1101 '
b10 "
b10 $
b10 #
#30
0!
b0 %
b0 '
b11 "
b11 $
b11 #
#40
1!
b1101 %
b1101 '
b1 &
b100 "
b100 $
b100 #
#50
0!
b1010 %
b1010 '
b101 "
b101 $
b101 #
#60
1!
b1101 %
b1101 '
b110 "
b110 $
b110 #
#70
0!
b0 %
b0 '
b111 "
b111 $
b111 #
#80
b1101 %
b1101 '
b10 &
b1000 "
b1000 $
b1000 #
#90
1!
b1010 %
b1010 '
b1001 "
b1001 $
b1001 #
#100
0!
b1101 %
b1101 '
b1010 "
b1010 $
b1010 #
#110
b0 %
b0 '
b1011 "
b1011 $
b1011 #
#120
1!
b1101 %
b1101 '
b11 &
b1100 "
b1100 $
b1100 #
#130
0!
b1010 %
b1010 '
b1101 "
b1101 $
b1101 #
#140
1!
b1101 %
b1101 '
b1110 "
b1110 $
b1110 #
#150
0!
b0 %
b0 '
b1111 "
b1111 $
b1111 #
#160
b10000 #
