DSD/Lab6/Q2/tFlipFlop.v
module tFlipFlop(t,clk,reset,q);
input t,clk,reset;
output reg q;
always@(negedge clk or reset)
begin
if(reset)
q<=0;

else if(t)
q<=~q;

end
endmodule

DSD/Lab6/Q2/tFlipFlop_tb.v
`timescale 1ns/1ns
`include "tFlipFlop.v"
module tFlipFlop_tb;
reg t,clk,reset;
wire q;
tFlipFlop tFF(t,clk,reset,q);
always #10 clk=~clk;
initial begin
$dumpfile("tFlipFlop_tb.vcd");
$dumpvars(0,tFlipFlop_tb);
clk=0;
#110 $finish;
end
initial begin
t=0;reset=0;#10;
t=1;reset=1;#10;
t=1;reset=0;#20;
t=1;reset=1;#10;
t=0;reset=1;#10;
t=1;reset=0;#20;
t=0;reset=0;#10;
t=0;reset=1;#20;
end
endmodule

DSD/Lab6/Q2/tFlipFlop_tb.vcd
$date
	Thu Oct  5 10:14:14 2023
$end
$version
	Icarus Verilog
$end
$timescale
	1ns
$end
$scope module tFlipFlop_tb $end
$var wire 1 ! q $end
$var reg 1 " clk $end
$var reg 1 # reset $end
$var reg 1 $ t $end
$scope module tFF $end
$var wire 1 " clk $end
$var wire 1 # reset $end
$var wire 1 $ t $end
$var reg 1 ! q $end
$upscope $end
$upscope $end
$enddefinitions $end
#0
$dumpvars
0$
0#
0"
0!
$end
#10
1#
1$
1"
#20
0!
0#
0"
#30
1"
#40
1!
0"
1#
#50
1"
0$
#60
0!
0"
0#
1$
#70
1"
#80
0"
0$
#90
1"
1#
