DSD/Lab1/q1a/q1a.v
module q1a(x1,x2,x3,x4,f);
input x1,x2,x3,x4;
output f;
assign f=x3|(x1&x4);
endmodule

DSD/Lab1/q1a/q1a_tb.v
`timescale 1ns/1ns
`include "q1a.v"
module q1a_tb;
reg x1,x2,x3,x4;
wire f;
q1a q1a1(x1,x2,x3,x4,f);
initial begin
	$dumpfile("q1a_tb.vcd");
	$dumpvars(0,q1a_tb);
	x1=0;
	x2=0;
	x3=0;
	x4=0;
	#5; 
	x1=0;
	x2=0;
	x3=0;
	x4=1;
	#5; 
	x1=0;
	x2=0;
	x3=1;
	x4=0;
	#5; 
	x1=0;
	x2=0;
	x3=1;
	x4=1;
	#5; 
	x1=0;
	x2=1;
	x3=0;
	x4=0;
	#5; 
	x1=0;
	x2=1;
	x3=0;
	x4=1;
	#5; 
	x1=0;
	x2=1;
	x3=1;
	x4=0;
	#5; 
	x1=0;
	x2=1;
	x3=1;
	x4=1;
	#5; 
	x1=1;
	x2=0;
	x3=0;
	x4=0;
	#5; 
	x1=1;
	x2=0;
	x3=0;
	x4=1;
	#5; 
	x1=1;
	x2=0;
	x3=1;
	x4=0;
	#5; 
	x1=1;
	x2=0;
	x3=1;
	x4=1;
	#5; 
	x1=1;
	x2=1;
	x3=0;
	x4=0;
	#5; 
	x1=1;
	x2=1;
	x3=0;
	x4=1;
	#5; 
	x1=1;
	x2=1;
	x3=1;
	x4=0;
	#5; 
	x1=1;
	x2=1;
	x3=1;
	x4=1;
	#5;
	$display("Test Completed");
end
endmodule

DSD/Lab1/q1a/q1a_tb.vcd
$date
	Thu Aug 10 09:32:57 2023
$end
$version
	Icarus Verilog
$end
$timescale
	1ns
$end
$scope module q1a_tb $end
$var wire 1 ! f $end
$var reg 1 " x1 $end
$var reg 1 # x2 $end
$var reg 1 $ x3 $end
$var reg 1 % x4 $end
$scope module q1a1 $end
$var wire 1 ! f $end
$var wire 1 " x1 $end
$var wire 1 # x2 $end
$var wire 1 $ x3 $end
$var wire 1 % x4 $end
$upscope $end
$upscope $end
$enddefinitions $end
#0
$dumpvars
0%
0$
0#
0"
0!
$end
#5
1%
#10
1!
0%
1$
#15
1%
#20
0!
0%
0$
1#
#25
1%
#30
1!
0%
1$
#35
1%
#40
0!
0%
0$
0#
1"
#45
1!
1%
#50
0%
1$
#55
1%
#60
0!
0%
0$
1#
#65
1!
1%
#70
0%
1$
#75
1%
