DSD/Lab7/Q2/regn.v
module regn(I,clk,Q);
parameter n=8;
input [n-1:0]I;
input clk;
output reg[n-1:0]Q;
always@(posedge clk)
	Q<=I;
endmodule

DSD/Lab7/Q2/regn_tb.v
`timescale 1ns/1ns
`include "regn.v"
module regn_tb;
parameter n=8;
integer i=2;
reg [n-1:0]I;
reg clk;
wire [n-1:0]Q;
regn r1(I,clk,Q);
always #10 clk=~clk;
initial begin
$dumpfile("regn_tb.vcd");
$dumpvars(0,regn_tb);
clk=0;
end
initial begin
for(i=2;i<128;i=i*2)
begin
I=i;
#20;
end
$finish;
end
endmodule

DSD/Lab7/Q2/regn_tb.vcd
$date
	Thu Oct 12 10:54:38 2023
$end
$version
	Icarus Verilog
$end
$timescale
	1ns
$end
$scope module regn_tb $end
$var wire 8 ! Q [7:0] $end
$var reg 8 " I [7:0] $end
$var reg 1 # clk $end
$var integer 32 $ i [31:0] $end
$scope module r1 $end
$var wire 8 % I [7:0] $end
$var wire 1 # clk $end
$var reg 8 & Q [7:0] $end
$upscope $end
$upscope $end
$enddefinitions $end
#0
$dumpvars
bx &
b10 %
b10 $
0#
b10 "
bx !
$end
#10
b10 !
b10 &
1#
#20
0#
b100 "
b100 %
b100 $
#30
b100 !
b100 &
1#
#40
0#
b1000 "
b1000 %
b1000 $
#50
b1000 !
b1000 &
1#
#60
0#
b10000 "
b10000 %
b10000 $
#70
b10000 !
b10000 &
1#
#80
0#
b100000 "
b100000 %
b100000 $
#90
b100000 !
b100000 &
1#
#100
0#
b1000000 "
b1000000 %
b1000000 $
#110
b1000000 !
b1000000 &
1#
#120
0#
b10000000 $
