DSD/Lab3/Q2/Mux2_1.v
module Mux2_1(W,s,f);
input [0:1]W;
input s;
output reg f;
always @(W or s)
f=s?W[1]:W[0];
endmodule

DSD/Lab5/Q2/Mux8_1.v
module Mux8_1(W,S,f);
input [0:7]W;
input [2:0]S;
output reg f;
always @*
	begin
	case(S)
	0:f=W[0];
	1:f=W[1];
	2:f=W[2];
	3:f=W[3];
	4:f=W[4];
	5:f=W[5];
	6:f=W[6];
	7:f=W[7];
	endcase
	end
endmodule

DSD/Lab3/Q2/Mux16_1.v
`include "Mux8_1.v"
`include "Mux2_1.v"
module Mux16_1(W,S,f);
input [0:15]W;
input [3:0]S;
wire [0:1]t;
output f;
Mux8_1 M1(W[0:7],S[2:0],t[0]);
Mux8_1 M2(W[8:15],S[2:0],t[1]);
Mux2_1 M3(t,S[3],f);
endmodule

DSD/Lab3/Q2/Mux16_1_tb.v
`timescale 1ns/1ns
`include "Mux16_1.v"
module Mux16_1_tb;
reg [0:15]W;
reg [3:0]S;
wire f;
Mux16_1 M1(W,S,f);
initial begin
$dumpfile("Mux16_1_tb.vcd");
$dumpvars(0,Mux16_1_tb);
	W=16'b1010101010101010;
	S=0;
	#20;
	W=16'b1010101010101010;
	S=1;
	#20;
	W=16'b1010101010101010;
	S=2;
	#20;
	W=16'b1010101010101010;
	S=3;
	#20;
	W=16'b1010101010101010;
	S=4;
	#20;
	W=16'b1010101010101010;
	S=5;
	#20;
	W=16'b1010101010101010;
	S=6;
	#20;
	W=16'b1010101010101010;
	S=7;
	#20;
	W=16'b1010101010101010;
	S=8;
	#20;
	W=16'b1010101010101010;
	S=9;
	#20;
	W=16'b1010101010101010;
	S=10;
	#20;
	W=16'b1010101010101010;
	S=11;
	#20;
	W=16'b1010101010101010;
	S=12;
	#20;
	W=16'b1010101010101010;
	S=13;
	#20;
	W=16'b1010101010101010;
	S=14;
	#20;
	W=16'b1010101010101010;
	S=15;
	#20;
end
endmodule

DSD/Lab3/Q2/Mux16_1_tb.vcd
$date
	Thu Aug 24 09:49:57 2023
$end
$version
	Icarus Verilog
$end
$timescale
	1ns
$end
$scope module Mux16_1_tb $end
$var wire 1 ! f $end
$var reg 4 " S [3:0] $end
$var reg 16 # W [0:15] $end
$scope module M1 $end
$var wire 4 $ S [3:0] $end
$var wire 16 % W [0:15] $end
$var wire 2 & t [0:1] $end
$var wire 1 ! f $end
$scope module M1 $end
$var wire 3 ' S [2:0] $end
$var wire 8 ( W [0:7] $end
$var reg 1 ) f $end
$upscope $end
$scope module M2 $end
$var wire 3 * S [2:0] $end
$var wire 8 + W [0:7] $end
$var reg 1 , f $end
$upscope $end
$scope module M3 $end
$var wire 2 - W [0:1] $end
$var wire 1 . s $end
$var reg 1 ! f $end
$upscope $end
$upscope $end
$upscope $end
$enddefinitions $end
#0
$dumpvars
0.
b11 -
1,
b10101010 +
b0 *
1)
b10101010 (
b0 '
b11 &
b1010101010101010 %
b0 $
b1010101010101010 #
b0 "
1!
$end
#20
0!
0)
b0 &
b0 -
0,
b1 '
b1 *
b1 "
b1 $
#40
1!
1)
b11 &
b11 -
1,
b10 '
b10 *
b10 "
b10 $
#60
0!
0)
b0 &
b0 -
0,
b11 '
b11 *
b11 "
b11 $
#80
1!
1)
b11 &
b11 -
1,
b100 '
b100 *
b100 "
b100 $
#100
0!
0)
b0 &
b0 -
0,
b101 '
b101 *
b101 "
b101 $
#120
1!
1)
b11 &
b11 -
1,
b110 '
b110 *
b110 "
b110 $
#140
0!
0)
b0 &
b0 -
0,
b111 '
b111 *
b111 "
b111 $
#160
1!
1)
b11 &
b11 -
1,
b0 '
b0 *
1.
b1000 "
b1000 $
#180
0!
0)
b0 &
b0 -
0,
b1 '
b1 *
b1001 "
b1001 $
#200
1!
1)
b11 &
b11 -
1,
b10 '
b10 *
b1010 "
b1010 $
#220
0!
0)
b0 &
b0 -
0,
b11 '
b11 *
b1011 "
b1011 $
#240
1!
1)
b11 &
b11 -
1,
b100 '
b100 *
b1100 "
b1100 $
#260
0!
0)
b0 &
b0 -
0,
b101 '
b101 *
b1101 "
b1101 $
#280
1!
1)
b11 &
b11 -
1,
b110 '
b110 *
b1110 "
b1110 $
#300
0!
0)
b0 &
b0 -
0,
b111 '
b111 *
b1111 "
b1111 $
