DSD/Lab5/Q2/Mux8_1.v
module Mux8_1(W,S,f);
input [0:7]W;
input [2:0]S;
output reg f;
always @*
	begin
	case(S)
	0:f=W[0];
	1:f=W[1];
	2:f=W[2];
	3:f=W[3];
	4:f=W[4];
	5:f=W[5];
	6:f=W[6];
	7:f=W[7];
	endcase
	end
endmodule

DSD/Lab5/Q2/q2.v
`include "Mux8_1.v"
module q2(G,B);
input [3:0]G;
output [3:0]B;
wire [0:7]M3,M2,M1,M0;
assign M3=8'b00001111;
assign M2=8'b00111100;
assign M1=8'b01101001;
assign M0={G[0],(~G[0]),(~G[0]),G[0],(~G[0]),G[0],G[0],(~G[0])};
Mux8_1 Mu3(M3,G[3:1],B[3]);
Mux8_1 Mu2(M2,G[3:1],B[2]);
Mux8_1 Mu1(M1,G[3:1],B[1]);
Mux8_1 Mu0(M0,G[3:1],B[0]);
endmodule

DSD/Lab5/Q2/q2_tb.v
`timescale 1ns/1ns
`include "q2.v"
module q2_tb;
reg [3:0]G;
wire [3:0]B;
integer i;
q2 q(G,B);
initial begin
$dumpfile("q2_tb.vcd");
$dumpvars(0,q2_tb);
for(i=0;i<16;i=i+1)
begin
G=i;
#10;
end
end
endmodule

DSD/Lab5/Q2/q2_tb.vcd
$date
	Thu Sep 14 10:07:23 2023
$end
$version
	Icarus Verilog
$end
$timescale
	1ns
$end
$scope module q2_tb $end
$var wire 4 ! B [3:0] $end
$var reg 4 " G [3:0] $end
$var integer 32 # i [31:0] $end
$scope module q $end
$var wire 4 $ G [3:0] $end
$var wire 8 % M1 [0:7] $end
$var wire 8 & M2 [0:7] $end
$var wire 8 ' M3 [0:7] $end
$var wire 8 ( M0 [0:7] $end
$var wire 4 ) B [3:0] $end
$scope module Mu0 $end
$var wire 3 * S [2:0] $end
$var wire 8 + W [0:7] $end
$var reg 1 , f $end
$upscope $end
$scope module Mu1 $end
$var wire 3 - S [2:0] $end
$var wire 8 . W [0:7] $end
$var reg 1 / f $end
$upscope $end
$scope module Mu2 $end
$var wire 3 0 S [2:0] $end
$var wire 8 1 W [0:7] $end
$var reg 1 2 f $end
$upscope $end
$scope module Mu3 $end
$var wire 3 3 S [2:0] $end
$var wire 8 4 W [0:7] $end
$var reg 1 5 f $end
$upscope $end
$upscope $end
$upscope $end
$enddefinitions $end
#0
$dumpvars
05
b1111 4
b0 3
02
b111100 1
b0 0
0/
b1101001 .
b0 -
0,
b1101001 +
b0 *
b0 )
b1101001 (
b1111 '
b111100 &
b1101001 %
b0 $
b0 #
b0 "
b0 !
$end
#10
b1 !
b1 )
1,
b10010110 (
b10010110 +
b1 "
b1 $
b1 #
#20
1/
b11 !
b11 )
1,
b1101001 (
b1101001 +
b1 3
b1 0
b1 -
b1 *
b10 "
b10 $
b10 #
#30
b10 !
b10 )
0,
b10010110 (
b10010110 +
b11 "
b11 $
b11 #
#40
1,
b111 !
b111 )
12
b1101001 (
b1101001 +
b10 3
b10 0
b10 -
b10 *
b100 "
b100 $
b100 #
#50
b110 !
b110 )
0,
b10010110 (
b10010110 +
b101 "
b101 $
b101 #
#60
b100 !
b100 )
0/
b1101001 (
b1101001 +
b11 3
b11 0
b11 -
b11 *
b110 "
b110 $
b110 #
#70
b101 !
b101 )
1,
b10010110 (
b10010110 +
b111 "
b111 $
b111 #
#80
15
1/
b1111 !
b1111 )
1,
b1101001 (
b1101001 +
b100 3
b100 0
b100 -
b100 *
b1000 "
b1000 $
b1000 #
#90
b1110 !
b1110 )
0,
b10010110 (
b10010110 +
b1001 "
b1001 $
b1001 #
#100
b1100 !
b1100 )
0/
b1101001 (
b1101001 +
b101 3
b101 0
b101 -
b101 *
b1010 "
b1010 $
b1010 #
#110
b1101 !
b1101 )
1,
b10010110 (
b10010110 +
b1011 "
b1011 $
b1011 #
#120
02
b1000 !
b1000 )
0,
b1101001 (
b1101001 +
b110 3
b110 0
b110 -
b110 *
b1100 "
b1100 $
b1100 #
#130
b1001 !
b1001 )
1,
b10010110 (
b10010110 +
b1101 "
b1101 $
b1101 #
#140
1/
b1011 !
b1011 )
1,
b1101001 (
b1101001 +
b111 3
b111 0
b111 -
b111 *
b1110 "
b1110 $
b1110 #
#150
b1010 !
b1010 )
0,
b10010110 (
b10010110 +
b1111 "
b1111 $
b1111 #
#160
b10000 #
