DSD/Lab4/penc4to2/penc4to2.v
module penc4to2(W,Y,z);
input [3:0]W;
output reg [1:0]Y;
output reg z;
always @*
begin
z=1;
casex(W)
4'b1xxx:Y=2'b11;
4'b01xx:Y=2'b10;
4'b001x:Y=2'b01;
4'b0001:Y=2'b00;
default:begin
z=0;
Y=2'bxx;
end
endcase
end
endmodule

DSD/Lab4/penc4to2/penc4to2_tb.v
`timescale 1ns/1ns
`include "penc4to2.v"
module penc4to2_tb;
reg [3:0]W;
wire [1:0]Y;
wire s;
integer i;
penc4to2 p(W,Y,z);
initial begin
$dumpfile("penc4to2_tb.vcd");
$dumpvars(0,penc4to2_tb);
for(i=0;i<16;i=i+1)
begin
W=i;
#10;
end
end
endmodule

DSD/Lab4/penc4to2/penc4to2_tb.vcd
$date
	Thu Aug 31 10:03:36 2023
$end
$version
	Icarus Verilog
$end
$timescale
	1ns
$end
$scope module penc4to2_tb $end
$var wire 1 ! z $end
$var wire 2 " Y [1:0] $end
$var reg 4 # W [3:0] $end
$var integer 32 $ i [31:0] $end
$scope module p $end
$var wire 4 % W [3:0] $end
$var reg 2 & Y [1:0] $end
$var reg 1 ! z $end
$upscope $end
$upscope $end
$enddefinitions $end
#0
$dumpvars
bx &
b0 %
b0 $
b0 #
bx "
0!
$end
#10
b0 "
b0 &
1!
b1 #
b1 %
b1 $
#20
b1 "
b1 &
b10 #
b10 %
b10 $
#30
b11 #
b11 %
b11 $
#40
b10 "
b10 &
b100 #
b100 %
b100 $
#50
b101 #
b101 %
b101 $
#60
b110 #
b110 %
b110 $
#70
b111 #
b111 %
b111 $
#80
b11 "
b11 &
b1000 #
b1000 %
b1000 $
#90
b1001 #
b1001 %
b1001 $
#100
b1010 #
b1010 %
b1010 $
#110
b1011 #
b1011 %
b1011 $
#120
b1100 #
b1100 %
b1100 $
#130
b1101 #
b1101 %
b1101 $
#140
b1110 #
b1110 %
b1110 $
#150
b1111 #
b1111 %
b1111 $
#160
b10000 $
