DSD/Lab6/Q2/tFlipFlop.v
module tFlipFlop(t,clk,reset,q);
input t,clk,reset;
output reg q;
always@(negedge clk or reset)
begin
if(reset)
q<=0;

else if(t)
q<=~q;

end
endmodule

DSD/Lab8/Q2/q2.v
`include "tFlipFlop.v"
module q2(x,A,clk,reset);
input x,clk,reset;
output [1:0]A;
wire [1:0]t;
assign t[1]=(A[0]&(~x))|((~A[1])&A[0]);
assign t[0]=(A[1]&(~x))|((~A[0])&(~x))|((~A[1])&(A[0])&x);
tFlipFlop t1(t[1],clk,reset,A[1]);
tFlipFlop t2(t[0],clk,reset,A[0]);
endmodule

DSD/Lab8/Q2/q2_tb.v
`timescale 1ns/1ns
`include "q2.v"
module q2_tb;
reg reset;
reg clk;
wire [1:0]A;
reg x;
q2 q(x,A,clk,reset);
always #10 clk=~clk;
initial begin
$dumpfile("q2_tb.vcd");
$dumpvars(0,q2_tb);
clk=0;
end
initial begin
	x=1'b0;reset=1'b1;#20;
	x=1'b1;reset=1'b0;#20;
	x=1'b0;reset=1'b0;#20;
	x=1'b1;reset=1'b0;#20;
	x=1'b0;reset=1'b0;#20;
	x=1'b1;reset=1'b0;#20;
	x=1'b0;reset=1'b0;#20;
	x=1'b1;reset=1'b0;#20;
	x=1'b0;reset=1'b0;#20;
	x=1'b1;reset=1'b0;#20;
$finish;
end
endmodule

DSD/Lab8/Q2/q2_tb.vcd
$date
	Thu Oct 19 11:02:47 2023
$end
$version
	Icarus Verilog
$end
$timescale
	1ns
$end
$scope module q2_tb $end
$var wire 2 ! A [1:0] $end
$var reg 1 " clk $end
$var reg 1 # reset $end
$var reg 1 $ x $end
$scope module q $end
$var wire 1 " clk $end
$var wire 1 # reset $end
$var wire 1 $ x $end
$var wire 2 % t [1:0] $end
$var wire 2 & A [1:0] $end
$scope module t1 $end
$var wire 1 " clk $end
$var wire 1 # reset $end
$var wire 1 ' t $end
$var reg 1 ( q $end
$upscope $end
$scope module t2 $end
$var wire 1 " clk $end
$var wire 1 # reset $end
$var wire 1 ) t $end
$var reg 1 * q $end
$upscope $end
$upscope $end
$upscope $end
$enddefinitions $end
#0
$dumpvars
x*
x)
x(
x'
bx &
bx %
0$
1#
0"
bx !
$end
#10
1"
#20
0)
0'
b0 %
0(
b0 !
b0 &
0*
0"
0#
1$
#30
1"
#40
1)
b1 %
0"
0$
#50
1"
#60
1'
b1 !
b1 &
1*
1)
b11 %
0"
1$
#70
1"
#80
0'
1(
b10 !
b10 &
0*
1)
b1 %
0"
0$
#90
1"
#100
b11 !
b11 &
1*
0)
b0 %
0"
1$
#110
1"
#120
1)
1'
b11 %
0"
0$
#130
1"
#140
0*
b0 !
b0 &
0(
0)
0'
b0 %
0"
1$
#150
1"
#160
1)
b1 %
0"
0$
#170
1"
#180
1'
b1 !
b1 &
1*
1)
b11 %
0"
1$
#190
1"
#200
0)
0'
b0 %
1(
b10 !
b10 &
0*
0"
