DSD/Lab4/dec2to4/dec2to4.v
module dec2to4(W,Y,En);
input [1:0]W;
input En;
output reg [0:3]Y;
always@*
begin
if(En==1)
begin
if(W==0)
Y=4'b1000;
else if(W==1)
Y=4'b0100;
else if(W==2)
Y=4'b0010;
else
Y=4'b0001;
end
else
Y=4'b0000;
end
endmodule

DSD/Lab5/Q4/q4.v
`include "dec2to4.v"
module q4(W,f);
input [0:2]W;
output f;
wire [0:3]Y;
dec2to4 d(W[0:1],Y,1'b1);
assign f=((Y[0]&0)|(Y[1]&W[2])|(Y[2]&W[2])|(Y[3]&1));
endmodule

DSD/Lab5/Q4/q4_tb.v
`timescale 1ns/1ns
`include "q4.v"
module q4_tb;
reg [0:2]W;
wire f;
integer i;
q4 q(W,f);
initial begin
$dumpfile("q4_tb.vcd");
$dumpvars(0,q4_tb);
for(i=0;i<8;i++)
begin
W=i;
#5;
end
end
endmodule

DSD/Lab5/Q4/q4_tb.vcd
$date
	Thu Sep 14 11:09:47 2023
$end
$version
	Icarus Verilog
$end
$timescale
	1ns
$end
$scope module q4_tb $end
$var wire 1 ! f $end
$var reg 3 " W [0:2] $end
$var integer 32 # i [31:0] $end
$scope module q $end
$var wire 3 $ W [0:2] $end
$var wire 1 ! f $end
$var wire 4 % Y [0:3] $end
$scope module d $end
$var wire 1 & En $end
$var wire 2 ' W [1:0] $end
$var reg 4 ( Y [0:3] $end
$upscope $end
$upscope $end
$upscope $end
$enddefinitions $end
#0
$dumpvars
b1000 (
b0 '
1&
b1000 %
b0 $
b0 #
b0 "
0!
$end
#5
b1 "
b1 $
b1 #
#10
b100 %
b100 (
b1 '
b10 "
b10 $
b10 #
#15
1!
b11 "
b11 $
b11 #
#20
0!
b10 %
b10 (
b10 '
b100 "
b100 $
b100 #
#25
1!
b101 "
b101 $
b101 #
#30
1!
b1 %
b1 (
b11 '
b110 "
b110 $
b110 #
#35
b111 "
b111 $
b111 #
#40
b1000 #
