DSD/Lab9/Q3/tFlipFlop.v
module tFlipFlop(t,clk,reset,q);
input t,clk,reset;
output reg q;
always@(negedge clk)
begin
if(t)
q<=~q;
end
always@(reset)
begin
if(reset)
q<=0;
end
endmodule

DSD/Lab9/Q3/Q3.v
`include "tFlipFlop.v"
module Q3(clk,reset,c);
input clk,reset;
output [3:0]c;

tFlipFlop t1(1'b1,clk,reset,c[0]);
tFlipFlop t2(1'b1,c[0],reset,c[1]);
tFlipFlop t3(1'b1,c[1],reset,c[2]);
tFlipFlop t4(1'b1,c[2],reset,c[3]);

endmodule

DSD/Lab9/Q3/Q3_tb.v
`timescale 1ns/1ns
`include "Q3.v"
module Q3_tb;
reg reset,clk;
wire [3:0]c;
Q3 R(clk,reset,c);
always #10 clk=~clk;
initial begin
$dumpfile("Q3_tb.vcd");
$dumpvars(0,Q3_tb);
clk=0;
end
initial begin
	reset=1'b1;#20;
	reset=1'b0;#20;
	reset=1'b0;#20;
	reset=1'b0;#20;
	reset=1'b0;#20;
	reset=1'b0;#20;
	reset=1'b0;#20;
	reset=1'b0;#20;
	reset=1'b0;#20;
	reset=1'b0;#20;
	reset=1'b0;#20;
	reset=1'b0;#20;
$finish;
end
endmodule

DSD/Lab9/Q3/Q3_tb.vcd
$date
	Thu Oct 26 11:10:31 2023
$end
$version
	Icarus Verilog
$end
$timescale
	1ns
$end
$scope module Q3_tb $end
$var wire 4 ! c [3:0] $end
$var reg 1 " clk $end
$var reg 1 # reset $end
$scope module R $end
$var wire 1 " clk $end
$var wire 1 # reset $end
$var wire 4 $ c [3:0] $end
$scope module t1 $end
$var wire 1 " clk $end
$var wire 1 # reset $end
$var wire 1 % t $end
$var reg 1 & q $end
$upscope $end
$scope module t2 $end
$var wire 1 ' clk $end
$var wire 1 # reset $end
$var wire 1 ( t $end
$var reg 1 ) q $end
$upscope $end
$scope module t3 $end
$var wire 1 * clk $end
$var wire 1 # reset $end
$var wire 1 + t $end
$var reg 1 , q $end
$upscope $end
$scope module t4 $end
$var wire 1 - clk $end
$var wire 1 # reset $end
$var wire 1 . t $end
$var reg 1 / q $end
$upscope $end
$upscope $end
$upscope $end
$enddefinitions $end
#0
$dumpvars
1/
1.
1-
1,
1+
1*
1)
1(
0'
0&
1%
b1110 $
1#
0"
b1110 !
$end
#10
1"
#20
1'
b1111 !
b1111 $
1&
0"
0#
#30
1"
#40
0/
0-
0,
0*
0)
0'
b0 !
b0 $
0&
0"
#50
1"
#60
1'
b1 !
b1 $
1&
0"
#70
1"
#80
1*
1)
0'
b10 !
b10 $
0&
0"
#90
1"
#100
1'
b11 !
b11 $
1&
0"
#110
1"
#120
1-
1,
0*
0)
0'
b100 !
b100 $
0&
0"
#130
1"
#140
1'
b101 !
b101 $
1&
0"
#150
1"
#160
1*
1)
0'
b110 !
b110 $
0&
0"
#170
1"
#180
1'
b111 !
b111 $
1&
0"
#190
1"
#200
1/
0-
0,
0*
0)
0'
b1000 !
b1000 $
0&
0"
#210
1"
#220
1'
b1001 !
b1001 $
1&
0"
#230
1"
#240
1*
1)
0'
b1010 !
b1010 $
0&
0"
