DSD/Demo/example_2.v
module example_2(x1,x2,x3,f);
input x1,x2,x3;
output f;
assign f=(x1&x2)|(~x2&x3);
endmodule

DSD/Demo/example_2_tb.v
`timescale 1ns/1ns
`include "example_2.v"
module example_2_tb;
reg x1,x2,x3;
wire f;
example_2 e2(x1,x2,x3,f);
initial begin
	$dumpfile("example_2_tb.vcd");
	$dumpvars(0,example_2_tb);
	
	x1=0;
	x2=0;
	x3=0;
	#10;
	x1=0;
	x2=0;
	x3=1;
	#10;
	x1=0;
	x2=1;
	x3=0;
	#10;
	x1=0;
	x2=1;
	x3=1;
	#10;
	x1=1;
	x2=0;
	x3=0;
	#10;
	x1=1;
	x2=0;
	x3=1;
	#10;
	x1=1;
	x2=1;
	x3=0;
	#10;
	x1=1;
	x2=1;
	x3=1;
	#10;
	
	$display("Example_2_excuted");
end
endmodule

DSD/Demo/example_2_tb.vcd
$date
	Thu Aug  3 10:21:47 2023
$end
$version
	Icarus Verilog
$end
$timescale
	1ns
$end
$scope module example_2_tb $end
$var wire 1 ! f $end
$var reg 1 " x1 $end
$var reg 1 # x2 $end
$var reg 1 $ x3 $end
$scope module e2 $end
$var wire 1 ! f $end
$var wire 1 " x1 $end
$var wire 1 # x2 $end
$var wire 1 $ x3 $end
$upscope $end
$upscope $end
$enddefinitions $end
#0
$dumpvars
0$
0#
0"
0!
$end
#10
1!
1$
#20
0!
0$
1#
#30
1$
#40
0$
0#
1"
#50
1!
1$
#60
0$
1#
#70
1$
