DSD/Demo/example_1.v
module example_1(x1,x2,x3,f);
	input x1,x2,x3;
	output f;
	and(g,x1,x2);
	and(h,~x2,x3);
	or(f,g,h);
endmodule

DSD/Demo/example_1_tb.v
`timescale 1ns/1ns
`include "example_1.v"
module example_1_tb;
reg x1,x2,x3;
wire f;
example_1 e1(x1,x2,x3,f);
initial begin
	$dumpfile("example_1_tb.vcd");
	$dumpvars(0,example_1_tb);
	
	x1=0;
	x2=0;
	x3=0;
	#10;
	x1=0;
	x2=0;
	x3=1;
	#10;
	x1=0;
	x2=1;
	x3=0;
	#10;
	x1=0;
	x2=1;
	x3=1;
	#10;
	x1=1;
	x2=0;
	x3=0;
	#10;
	x1=1;
	x2=0;
	x3=1;
	#10;
	x1=1;
	x2=1;
	x3=0;
	#10;
	x1=1;
	x2=1;
	x3=1;
	#10;
	
	$display("Example_1_excuted");
end
endmodule

DSD/Demo/example_1_tb.vcd
$date
	Thu Aug  3 15:42:08 2023
$end
$version
	Icarus Verilog
$end
$timescale
	1ns
$end
$scope module example_1_tb $end
$var wire 1 ! f $end
$var reg 1 " x1 $end
$var reg 1 # x2 $end
$var reg 1 $ x3 $end
$scope module e1 $end
$var wire 1 ! f $end
$var wire 1 % g $end
$var wire 1 & h $end
$var wire 1 " x1 $end
$var wire 1 # x2 $end
$var wire 1 $ x3 $end
$upscope $end
$upscope $end
$enddefinitions $end
#0
$dumpvars
0&
0%
0$
0#
0"
0!
$end
#10
1!
1&
1$
#20
0!
0&
0$
1#
#30
1$
#40
0$
0#
1"
#50
1!
1&
1$
#60
0&
1%
0$
1#
#70
1$
