DSD/Demo/question2.v
module question2(x1,x2,x3,x4,f);
input x1,x2,x3,x4;
output g,h,f;
assign g=(x1&x3)|(x2&x4);
assign h=(x1|(~x3))&((~x2)|x4);
assign f=g|h;
endmodule

DSD/Demo/question2_tb.v
`timescale 1ns/1ns
`include "question2.v"
module question2_tb;
reg x1,x2,x3,x4;
wire f;
question2 q2(x1,x2,x3,x4,f);
initial begin
$dumpfile("question2_tb.vcd");
$dumpvars(0,question2_tb);
	x1=0;
	x2=0;
	x3=0;
	x4=0;
	#5; 
	x1=0;
	x2=0;
	x3=0;
	x4=1;
	#5; 
	x1=0;
	x2=0;
	x3=1;
	x4=0;
	#5; 
	x1=0;
	x2=0;
	x3=1;
	x4=1;
	#5; 
	x1=0;
	x2=1;
	x3=0;
	x4=0;
	#5; 
	x1=0;
	x2=1;
	x3=0;
	x4=1;
	#5; 
	x1=0;
	x2=1;
	x3=1;
	x4=0;
	#5; 
	x1=0;
	x2=1;
	x3=1;
	x4=1;
	#5; 
	x1=1;
	x2=0;
	x3=0;
	x4=0;
	#5; 
	x1=1;
	x2=0;
	x3=0;
	x4=1;
	#5; 
	x1=1;
	x2=0;
	x3=1;
	x4=0;
	#5; 
	x1=1;
	x2=0;
	x3=1;
	x4=1;
	#5; 
	x1=1;
	x2=1;
	x3=0;
	x4=0;
	#5; 
	x1=1;
	x2=1;
	x3=0;
	x4=1;
	#5; 
	x1=1;
	x2=1;
	x3=1;
	x4=0;
	#5; 
	x1=1;
	x2=1;
	x3=1;
	x4=1;
	#5; 
	$display("Completed");
end
endmodule

DSD/Demo/question2_tb.vcd
$date
	Thu Aug  3 10:59:00 2023
$end
$version
	Icarus Verilog
$end
$timescale
	1ns
$end
$scope module question2_tb $end
$var wire 1 ! f $end
$var reg 1 " x1 $end
$var reg 1 # x2 $end
$var reg 1 $ x3 $end
$var reg 1 % x4 $end
$scope module q2 $end
$var wire 1 ! f $end
$var wire 1 & g $end
$var wire 1 ' h $end
$var wire 1 " x1 $end
$var wire 1 # x2 $end
$var wire 1 $ x3 $end
$var wire 1 % x4 $end
$upscope $end
$upscope $end
$enddefinitions $end
#0
$dumpvars
1'
0&
0%
0$
0#
0"
1!
$end
#5
1%
#10
0!
0'
0%
1$
#15
1%
#20
0%
0$
1#
#25
1!
1&
1'
1%
#30
0!
0&
0'
0%
1$
#35
1!
1&
1%
#40
0&
1'
0%
0$
0#
1"
#45
1%
#50
1&
0%
1$
#55
1%
#60
0!
0'
0&
0%
0$
1#
#65
1!
1&
1'
1%
#70
0'
0%
1$
#75
1'
1%
